{
  "asset_code": "001820",
  "asset_name": "삼화콘덴서",
  "asset_type": "stock",
  "base_date": "2026-01-08",
  "base_date_adjusted": false,
  "series": [
    {
      "close": 28450.0,
      "date": "2026-01-08",
      "rebased_return_pct": 0.0,
      "relative_trading_value": 1.0,
      "trading_value": 1796076950.0
    },
    {
      "close": 28350.0,
      "date": "2026-01-09",
      "rebased_return_pct": -0.35149384885764495,
      "relative_trading_value": 0.5211535897724204,
      "trading_value": 936031950.0
    },
    {
      "close": 29200.0,
      "date": "2026-01-12",
      "rebased_return_pct": 2.6362038664323375,
      "relative_trading_value": 1.075868095887393,
      "trading_value": 1469694400.0
    },
    {
      "close": 29050.0,
      "date": "2026-01-13",
      "rebased_return_pct": 2.10896309314587,
      "relative_trading_value": 0.7993617883064635,
      "trading_value": 1119587000.0
    },
    {
      "close": 28850.0,
      "date": "2026-01-14",
      "rebased_return_pct": 1.4059753954305798,
      "relative_trading_value": 0.9080604743463376,
      "trading_value": 1208036050.0
    },
    {
      "close": 29100.0,
      "date": "2026-01-15",
      "rebased_return_pct": 2.2847100175746924,
      "relative_trading_value": 0.9371201499194489,
      "trading_value": 1223771400.0
    },
    {
      "close": 28800.0,
      "date": "2026-01-16",
      "rebased_return_pct": 1.2302284710017575,
      "relative_trading_value": 0.8662958712745331,
      "trading_value": 1119427200.0
    },
    {
      "close": 29550.0,
      "date": "2026-01-19",
      "rebased_return_pct": 3.8664323374340945,
      "relative_trading_value": 1.3849954065735641,
      "trading_value": 1755506400.0
    },
    {
      "close": 29500.0,
      "date": "2026-01-20",
      "rebased_return_pct": 3.690685413005272,
      "relative_trading_value": 1.0214845528795615,
      "trading_value": 1357059000.0
    },
    {
      "close": 30400.0,
      "date": "2026-01-21",
      "rebased_return_pct": 6.854130052724078,
      "relative_trading_value": 3.3159747688112438,
      "trading_value": 4415843200.0
    },
    {
      "close": 31300.0,
      "date": "2026-01-22",
      "rebased_return_pct": 10.017574692442881,
      "relative_trading_value": 2.599148515247077,
      "trading_value": 4262872200.0
    },
    {
      "close": 31100.0,
      "date": "2026-01-23",
      "rebased_return_pct": 9.314586994727591,
      "relative_trading_value": 1.2757785686280534,
      "trading_value": 2396597100.0
    },
    {
      "close": 31150.0,
      "date": "2026-01-26",
      "rebased_return_pct": 9.490333919156415,
      "relative_trading_value": 0.804171180508321,
      "trading_value": 1545382650.0
    },
    {
      "close": 30800.0,
      "date": "2026-01-27",
      "rebased_return_pct": 8.260105448154658,
      "relative_trading_value": 0.8815317457280698,
      "trading_value": 1668528400.0
    },
    {
      "close": 31500.0,
      "date": "2026-01-28",
      "rebased_return_pct": 10.720562390158172,
      "relative_trading_value": 1.4603258191041895,
      "trading_value": 2740657500.0
    },
    {
      "close": 31950.0,
      "date": "2026-01-29",
      "rebased_return_pct": 12.302284710017574,
      "relative_trading_value": 1.9702304696034627,
      "trading_value": 3811091850.0
    },
    {
      "close": 31600.0,
      "date": "2026-01-30",
      "rebased_return_pct": 11.072056239015819,
      "relative_trading_value": 1.4997420571226825,
      "trading_value": 3076923600.0
    },
    {
      "close": 30200.0,
      "date": "2026-02-02",
      "rebased_return_pct": 6.151142355008787,
      "relative_trading_value": 1.7147372663863303,
      "trading_value": 3621433000.0
    },
    {
      "close": 33750.0,
      "date": "2026-02-03",
      "rebased_return_pct": 18.629173989455182,
      "relative_trading_value": 3.6050510048131548,
      "trading_value": 7915995000.0
    },
    {
      "close": 33150.0,
      "date": "2026-02-04",
      "rebased_return_pct": 16.520210896309315,
      "relative_trading_value": 1.8360512417583934,
      "trading_value": 4584379800.0
    },
    {
      "close": 31950.0,
      "date": "2026-02-05",
      "rebased_return_pct": 12.302284710017574,
      "relative_trading_value": 1.0581689472003573,
      "trading_value": 2752556400.0
    },
    {
      "close": 31000.0,
      "date": "2026-02-06",
      "rebased_return_pct": 8.963093145869948,
      "relative_trading_value": 0.8527645944917084,
      "trading_value": 2259032000.0
    },
    {
      "close": 33050.0,
      "date": "2026-02-09",
      "rebased_return_pct": 16.16871704745167,
      "relative_trading_value": 1.6392696793468156,
      "trading_value": 4450975700.0
    },
    {
      "close": 35000.0,
      "date": "2026-02-10",
      "rebased_return_pct": 23.022847100175746,
      "relative_trading_value": 5.359505753896371,
      "trading_value": 15351140000.0
    },
    {
      "close": 38000.0,
      "date": "2026-02-11",
      "rebased_return_pct": 33.567662565905096,
      "relative_trading_value": 9.731567759479573,
      "trading_value": 34798728000.0
    },
    {
      "close": 37200.0,
      "date": "2026-02-12",
      "rebased_return_pct": 30.755711775043938,
      "relative_trading_value": 2.2779199573850493,
      "trading_value": 11971369200.0
    },
    {
      "close": 36600.0,
      "date": "2026-02-13",
      "rebased_return_pct": 28.646748681898064,
      "relative_trading_value": 0.9612785731389656,
      "trading_value": 5568470400.0
    },
    {
      "close": 41650.0,
      "date": "2026-02-19",
      "rebased_return_pct": 46.397188049209134,
      "relative_trading_value": 3.3948280858497997,
      "trading_value": 20420661800.0
    },
    {
      "close": 43850.0,
      "date": "2026-02-20",
      "rebased_return_pct": 54.13005272407732,
      "relative_trading_value": 2.1490049332826926,
      "trading_value": 14932328200.0
    },
    {
      "close": 57000.0,
      "date": "2026-02-23",
      "rebased_return_pct": 100.35149384885764,
      "relative_trading_value": 14.092142902965412,
      "trading_value": 107484273000.0
    },
    {
      "close": 60700.0,
      "date": "2026-02-24",
      "rebased_return_pct": 113.3567662565905,
      "relative_trading_value": 10.938260177051331,
      "trading_value": 139798291400.0
    },
    {
      "close": 57200.0,
      "date": "2026-02-25",
      "rebased_return_pct": 101.05448154657293,
      "relative_trading_value": 1.6405825695777705,
      "trading_value": 32085596400.0
    },
    {
      "close": 57300.0,
      "date": "2026-02-26",
      "rebased_return_pct": 101.40597539543057,
      "relative_trading_value": 0.9262295467634264,
      "trading_value": 19489620900.0
    },
    {
      "close": 53900.0,
      "date": "2026-02-27",
      "rebased_return_pct": 89.45518453427064,
      "relative_trading_value": 0.818777928386351,
      "trading_value": 17963253000.0
    },
    {
      "close": 49550.0,
      "date": "2026-03-03",
      "rebased_return_pct": 74.16520210896309,
      "relative_trading_value": 0.7428349763683387,
      "trading_value": 16902347350.0
    },
    {
      "close": 40100.0,
      "date": "2026-03-04",
      "rebased_return_pct": 40.94903339191564,
      "relative_trading_value": 0.8673862409494233,
      "trading_value": 20350549500.0
    },
    {
      "close": 45300.0,
      "date": "2026-03-05",
      "rebased_return_pct": 59.22671353251317,
      "relative_trading_value": 0.7738054138026793,
      "trading_value": 18794879400.0
    },
    {
      "close": 47400.0,
      "date": "2026-03-06",
      "rebased_return_pct": 66.60808435852373,
      "relative_trading_value": 0.6019575349833763,
      "trading_value": 15093961200.0
    },
    {
      "close": 43350.0,
      "date": "2026-03-09",
      "rebased_return_pct": 52.3725834797891,
      "relative_trading_value": 0.28908371451228937,
      "trading_value": 7414540650.0
    },
    {
      "close": 48100.0,
      "date": "2026-03-10",
      "rebased_return_pct": 69.06854130052724,
      "relative_trading_value": 0.6016351130799148,
      "trading_value": 15415905700.0
    },
    {
      "close": 49550.0,
      "date": "2026-03-11",
      "rebased_return_pct": 74.16520210896309,
      "relative_trading_value": 0.6762737718342794,
      "trading_value": 17694651850.0
    },
    {
      "close": 51400.0,
      "date": "2026-03-12",
      "rebased_return_pct": 80.66783831282952,
      "relative_trading_value": 0.5786581058551229,
      "trading_value": 15572863600.0
    },
    {
      "close": 50600.0,
      "date": "2026-03-13",
      "rebased_return_pct": 77.85588752196837,
      "relative_trading_value": 0.29451707730869553,
      "trading_value": 8122109600.0
    },
    {
      "close": 51300.0,
      "date": "2026-03-16",
      "rebased_return_pct": 80.31634446397187,
      "relative_trading_value": 0.3061892571582394,
      "trading_value": 8500204800.0
    },
    {
      "close": 53900.0,
      "date": "2026-03-17",
      "rebased_return_pct": 89.45518453427064,
      "relative_trading_value": 1.1342307890469887,
      "trading_value": 31099168100.0
    },
    {
      "close": 61500.0,
      "date": "2026-03-18",
      "rebased_return_pct": 116.16871704745166,
      "relative_trading_value": 3.716597087897745,
      "trading_value": 101216884500.0
    },
    {
      "close": 60300.0,
      "date": "2026-03-19",
      "rebased_return_pct": 111.95079086115993,
      "relative_trading_value": 0.7859425334603086,
      "trading_value": 24911256600.0
    },
    {
      "close": 58400.0,
      "date": "2026-03-20",
      "rebased_return_pct": 105.27240773286468,
      "relative_trading_value": 0.5584830089860137,
      "trading_value": 18241824000.0
    },
    {
      "close": 53500.0,
      "date": "2026-03-23",
      "rebased_return_pct": 88.04920913884007,
      "relative_trading_value": 0.4177651532585859,
      "trading_value": 13600021000.0
    },
    {
      "close": 54400.0,
      "date": "2026-03-24",
      "rebased_return_pct": 91.21265377855887,
      "relative_trading_value": 0.3878072640786618,
      "trading_value": 12598931200.0
    },
    {
      "close": 55700.0,
      "date": "2026-03-25",
      "rebased_return_pct": 95.78207381370825,
      "relative_trading_value": 0.37220944808425377,
      "trading_value": 10326334400.0
    },
    {
      "close": 57400.0,
      "date": "2026-03-26",
      "rebased_return_pct": 101.75746924428823,
      "relative_trading_value": 0.8488069340205395,
      "trading_value": 18053907200.0
    },
    {
      "close": 56100.0,
      "date": "2026-03-27",
      "rebased_return_pct": 97.18804920913884,
      "relative_trading_value": 0.6925246495645851,
      "trading_value": 14243958300.0
    },
    {
      "close": 54200.0,
      "date": "2026-03-30",
      "rebased_return_pct": 90.50966608084359,
      "relative_trading_value": 0.4772650260234585,
      "trading_value": 9691285200.0
    },
    {
      "close": 51900.0,
      "date": "2026-03-31",
      "rebased_return_pct": 82.42530755711776,
      "relative_trading_value": 0.4323043382961223,
      "trading_value": 8599518600.0
    },
    {
      "close": 57800.0,
      "date": "2026-04-01",
      "rebased_return_pct": 103.1634446397188,
      "relative_trading_value": 0.6852205779720169,
      "trading_value": 13346135600.0
    },
    {
      "close": 53700.0,
      "date": "2026-04-02",
      "rebased_return_pct": 88.75219683655537,
      "relative_trading_value": 0.5493612148156396,
      "trading_value": 10507586400.0
    },
    {
      "close": 56900.0,
      "date": "2026-04-03",
      "rebased_return_pct": 100.0,
      "relative_trading_value": 0.6876328631047242,
      "trading_value": 12867366000.0
    },
    {
      "close": 55900.0,
      "date": "2026-04-06",
      "rebased_return_pct": 96.48506151142355,
      "relative_trading_value": 0.295442132970134,
      "trading_value": 5495584900.0
    },
    {
      "close": 55800.0,
      "date": "2026-04-07",
      "rebased_return_pct": 96.1335676625659,
      "relative_trading_value": 0.915211944276076,
      "trading_value": 16936248600.0
    },
    {
      "close": 60100.0,
      "date": "2026-04-08",
      "rebased_return_pct": 111.24780316344464,
      "relative_trading_value": 0.9305181296899775,
      "trading_value": 17290229100.0
    },
    {
      "close": 58400.0,
      "date": "2026-04-09",
      "rebased_return_pct": 105.27240773286468,
      "relative_trading_value": 0.46678289489222,
      "trading_value": 8663990400.0
    },
    {
      "close": 63100.0,
      "date": "2026-04-10",
      "rebased_return_pct": 121.79261862917399,
      "relative_trading_value": 2.3673757465137193,
      "trading_value": 43123234100.0
    },
    {
      "close": 62200.0,
      "date": "2026-04-13",
      "rebased_return_pct": 118.62917398945518,
      "relative_trading_value": 0.7216261459860018,
      "trading_value": 14407759200.0
    },
    {
      "close": 63700.0,
      "date": "2026-04-14",
      "rebased_return_pct": 123.90158172231986,
      "relative_trading_value": 1.5698869636254102,
      "trading_value": 31807575800.0
    },
    {
      "close": 63700.0,
      "date": "2026-04-15",
      "rebased_return_pct": 123.90158172231986,
      "relative_trading_value": 1.0692752948923614,
      "trading_value": 21702526300.0
    },
    {
      "close": 65700.0,
      "date": "2026-04-16",
      "rebased_return_pct": 130.93145869947276,
      "relative_trading_value": 1.2043309263915267,
      "trading_value": 19655600400.0
    },
    {
      "close": 64800.0,
      "date": "2026-04-17",
      "rebased_return_pct": 127.76801405975395,
      "relative_trading_value": 0.8480464972481704,
      "trading_value": 13617914400.0
    },
    {
      "close": 63100.0,
      "date": "2026-04-20",
      "rebased_return_pct": 121.79261862917399,
      "relative_trading_value": 0.6447673909203655,
      "trading_value": 10204595100.0
    },
    {
      "close": 66900.0,
      "date": "2026-04-21",
      "rebased_return_pct": 135.14938488576448,
      "relative_trading_value": 1.687423546964612,
      "trading_value": 26420014200.0
    },
    {
      "close": 65400.0,
      "date": "2026-04-22",
      "rebased_return_pct": 129.87697715289983,
      "relative_trading_value": 0.9321021300045089,
      "trading_value": 15238069200.0
    },
    {
      "close": 62100.0,
      "date": "2026-04-23",
      "rebased_return_pct": 118.27768014059754,
      "relative_trading_value": 1.1836182781419111,
      "trading_value": 19640553300.0
    },
    {
      "close": 63600.0,
      "date": "2026-04-24",
      "rebased_return_pct": 123.55008787346222,
      "relative_trading_value": 0.47412228409335516,
      "trading_value": 7905034800.0
    },
    {
      "close": 62900.0,
      "date": "2026-04-27",
      "rebased_return_pct": 121.0896309314587,
      "relative_trading_value": 0.4656688047398815,
      "trading_value": 7616498100.0
    },
    {
      "close": 64800.0,
      "date": "2026-04-28",
      "rebased_return_pct": 127.76801405975395,
      "relative_trading_value": 0.8171019849805305,
      "trading_value": 13279788000.0
    },
    {
      "close": 71000.0,
      "date": "2026-04-29",
      "rebased_return_pct": 149.56063268892794,
      "relative_trading_value": 3.8712692463478042,
      "trading_value": 63822965000.0
    },
    {
      "close": 67200.0,
      "date": "2026-04-30",
      "rebased_return_pct": 136.20386643233743,
      "relative_trading_value": 0.950707788393705,
      "trading_value": 18073104000.0
    },
    {
      "close": 68400.0,
      "date": "2026-05-04",
      "rebased_return_pct": 140.42179261862918,
      "relative_trading_value": 0.6698555940433296,
      "trading_value": 12987450000.0
    },
    {
      "close": 66900.0,
      "date": "2026-05-06",
      "rebased_return_pct": 135.14938488576448,
      "relative_trading_value": 0.6583296059521629,
      "trading_value": 12767931900.0
    },
    {
      "close": 67900.0,
      "date": "2026-05-07",
      "rebased_return_pct": 138.66432337434097,
      "relative_trading_value": 0.5606047562549706,
      "trading_value": 11076459100.0
    },
    {
      "close": 66000.0,
      "date": "2026-05-08",
      "rebased_return_pct": 131.9859402460457,
      "relative_trading_value": 0.43591388806804793,
      "trading_value": 8485092000.0
    },
    {
      "close": 64100.0,
      "date": "2026-05-11",
      "rebased_return_pct": 125.30755711775043,
      "relative_trading_value": 0.500928451825542,
      "trading_value": 9530067500.0
    },
    {
      "close": 63500.0,
      "date": "2026-05-12",
      "rebased_return_pct": 123.19859402460457,
      "relative_trading_value": 0.8310332357913898,
      "trading_value": 15846234500.0
    },
    {
      "close": 64000.0,
      "date": "2026-05-13",
      "rebased_return_pct": 124.95606326889279,
      "relative_trading_value": 0.6245944747572088,
      "trading_value": 11057984000.0
    },
    {
      "close": 67100.0,
      "date": "2026-05-14",
      "rebased_return_pct": 135.8523725834798,
      "relative_trading_value": 1.8659911047442383,
      "trading_value": 32723462200.0
    },
    {
      "close": 65200.0,
      "date": "2026-05-15",
      "rebased_return_pct": 129.1739894551845,
      "relative_trading_value": 1.7917777786169928,
      "trading_value": 31504053200.0
    },
    {
      "close": 62500.0,
      "date": "2026-05-18",
      "rebased_return_pct": 119.68365553602811,
      "relative_trading_value": 0.9655442745025379,
      "trading_value": 17449937500.0
    },
    {
      "close": 63900.0,
      "date": "2026-05-19",
      "rebased_return_pct": 124.60456942003515,
      "relative_trading_value": 0.9452684403325968,
      "trading_value": 16979252400.0
    },
    {
      "close": 78600.0,
      "date": "2026-05-20",
      "rebased_return_pct": 176.27416520210897,
      "relative_trading_value": 12.759470671714395,
      "trading_value": 231334655400.0
    },
    {
      "close": 78500.0,
      "date": "2026-05-21",
      "rebased_return_pct": 175.92267135325133,
      "relative_trading_value": 3.4734241801337578,
      "trading_value": 101378589500.0
    },
    {
      "close": 102000.0,
      "date": "2026-05-22",
      "rebased_return_pct": 258.52372583479786,
      "relative_trading_value": 8.197694708338798,
      "trading_value": 269989920000.0
    },
    {
      "close": 132600.0,
      "date": "2026-05-26",
      "rebased_return_pct": 366.0808435852373,
      "relative_trading_value": 5.622454991830368,
      "trading_value": 256791303600.0
    },
    {
      "close": 125900.0,
      "date": "2026-05-27",
      "rebased_return_pct": 342.53075571177504,
      "relative_trading_value": 6.571143074838684,
      "trading_value": 378037789700.0
    },
    {
      "close": 156200.0,
      "date": "2026-05-28",
      "rebased_return_pct": 449.03339191564146,
      "relative_trading_value": 11.195846114314113,
      "trading_value": 851294373600.0
    },
    {
      "close": 149100.0,
      "date": "2026-05-29",
      "rebased_return_pct": 424.0773286467487,
      "relative_trading_value": 7.897485240524633,
      "trading_value": 933644817000.0
    },
    {
      "close": 114000.0,
      "date": "2026-06-01",
      "rebased_return_pct": 300.7029876977153,
      "relative_trading_value": 2.1424684652113744,
      "trading_value": 351876390000.0
    },
    {
      "close": 107700.0,
      "date": "2026-06-02",
      "rebased_return_pct": 278.55887521968367,
      "relative_trading_value": 1.0296745802398468,
      "trading_value": 183942553200.0
    },
    {
      "close": 110400.0,
      "date": "2026-06-04",
      "rebased_return_pct": 288.04920913884007,
      "relative_trading_value": 0.5688116954310994,
      "trading_value": 106330766400.0
    },
    {
      "close": 111800.0,
      "date": "2026-06-05",
      "rebased_return_pct": 292.97012302284713,
      "relative_trading_value": 0.9054143666897954,
      "trading_value": 173479277400.0
    },
    {
      "close": 109200.0,
      "date": "2026-06-08",
      "rebased_return_pct": 283.8312829525483,
      "relative_trading_value": 0.41947209285034454,
      "trading_value": 83742422400.0
    },
    {
      "close": 118500.0,
      "date": "2026-06-09",
      "rebased_return_pct": 316.5202108963093,
      "relative_trading_value": 0.523317276918827,
      "trading_value": 106375198500.0
    },
    {
      "close": 109600.0,
      "date": "2026-06-10",
      "rebased_return_pct": 285.2372583479789,
      "relative_trading_value": 0.25181488376502575,
      "trading_value": 52419159200.0
    },
    {
      "close": 133300.0,
      "date": "2026-06-11",
      "rebased_return_pct": 368.54130052724076,
      "relative_trading_value": 1.0925958885826,
      "trading_value": 229783739700.0
    },
    {
      "close": 128200.0,
      "date": "2026-06-12",
      "rebased_return_pct": 350.61511423550087,
      "relative_trading_value": 0.6407831043076684,
      "trading_value": 141617412000.0
    },
    {
      "close": 140600.0,
      "date": "2026-06-15",
      "rebased_return_pct": 394.20035149384887,
      "relative_trading_value": 0.7737615022744408,
      "trading_value": 176057632800.0
    },
    {
      "close": 147900.0,
      "date": "2026-06-16",
      "rebased_return_pct": 419.8594024604569,
      "relative_trading_value": 0.5514606509076385,
      "trading_value": 129428621100.0
    },
    {
      "close": 151400.0,
      "date": "2026-06-17",
      "rebased_return_pct": 432.1616871704745,
      "relative_trading_value": 0.39871473206913055,
      "trading_value": 95531129000.0
    },
    {
      "close": 190100.0,
      "date": "2026-06-18",
      "rebased_return_pct": 568.1898066783831,
      "relative_trading_value": 3.2383766758573005,
      "trading_value": 788550388200.0
    },
    {
      "close": 171500.0,
      "date": "2026-06-19",
      "rebased_return_pct": 502.81195079086115,
      "relative_trading_value": 0.8477482373666859,
      "trading_value": 239133083000.0
    },
    {
      "close": 167000.0,
      "date": "2026-06-22",
      "rebased_return_pct": 486.9947275922671,
      "relative_trading_value": 0.33769126243501757,
      "trading_value": 95387728000.0
    },
    {
      "close": 142000.0,
      "date": "2026-06-23",
      "rebased_return_pct": 399.1212653778559,
      "relative_trading_value": 0.37289843170811443,
      "trading_value": 105221006000.0
    },
    {
      "close": 136000.0,
      "date": "2026-06-24",
      "rebased_return_pct": 378.0316344463972,
      "relative_trading_value": 0.2493402314188958,
      "trading_value": 68302328000.0
    },
    {
      "close": 131900.0,
      "date": "2026-06-25",
      "rebased_return_pct": 363.62038664323376,
      "relative_trading_value": 0.2366670086356741,
      "trading_value": 62600267600.0
    },
    {
      "close": 130600.0,
      "date": "2026-06-26",
      "rebased_return_pct": 359.05096660808437,
      "relative_trading_value": 0.3179732211558623,
      "trading_value": 79091360000.0
    },
    {
      "close": 133000.0,
      "date": "2026-06-29",
      "rebased_return_pct": 367.48681898066786,
      "relative_trading_value": 0.1876620803372382,
      "trading_value": 39432638000.0
    },
    {
      "close": 151000.0,
      "date": "2026-06-30",
      "rebased_return_pct": 430.75571177504395,
      "relative_trading_value": 1.174714360184423,
      "trading_value": 194315558000.0
    },
    {
      "close": 155500.0,
      "date": "2026-07-01",
      "rebased_return_pct": 446.572934973638,
      "relative_trading_value": 1.609326170754674,
      "trading_value": 253528599500.0
    },
    {
      "close": 122200.0,
      "date": "2026-07-02",
      "rebased_return_pct": 329.5254833040422,
      "relative_trading_value": 0.9485859034809987,
      "trading_value": 152737902200.0
    },
    {
      "close": 119300.0,
      "date": "2026-07-03",
      "rebased_return_pct": 319.33216168717047,
      "relative_trading_value": 0.5917021501220672,
      "trading_value": 96646719500.0
    },
    {
      "close": 112700.0,
      "date": "2026-07-06",
      "rebased_return_pct": 296.1335676625659,
      "relative_trading_value": 0.5587390939325443,
      "trading_value": 89116172600.0
    }
  ]
}