{
  "asset_code": "050890",
  "asset_name": "쏠리드",
  "asset_type": "stock",
  "base_date": "2025-12-19",
  "base_date_adjusted": false,
  "series": [
    {
      "close": 7780.0,
      "date": "2025-12-19",
      "rebased_return_pct": 0.0,
      "relative_trading_value": 1.0,
      "trading_value": 4665666000.0
    },
    {
      "close": 8340.0,
      "date": "2025-12-22",
      "rebased_return_pct": 7.197943444730077,
      "relative_trading_value": 4.9480136083465895,
      "trading_value": 23085778860.0
    },
    {
      "close": 7750.0,
      "date": "2025-12-23",
      "rebased_return_pct": -0.3856041131105398,
      "relative_trading_value": 1.0662255118344854,
      "trading_value": 14794649250.0
    },
    {
      "close": 7600.0,
      "date": "2025-12-24",
      "rebased_return_pct": -2.313624678663239,
      "relative_trading_value": 0.5151713608147237,
      "trading_value": 7306176400.0
    },
    {
      "close": 7520.0,
      "date": "2025-12-26",
      "rebased_return_pct": -3.3419023136246784,
      "relative_trading_value": 0.5208773982479138,
      "trading_value": 6491730240.0
    },
    {
      "close": 7660.0,
      "date": "2025-12-29",
      "rebased_return_pct": -1.5424164524421593,
      "relative_trading_value": 0.37959851120440713,
      "trading_value": 4277619760.0
    },
    {
      "close": 7370.0,
      "date": "2025-12-30",
      "rebased_return_pct": -5.269922879177378,
      "relative_trading_value": 0.5568587638535893,
      "trading_value": 5626280110.0
    },
    {
      "close": 7820.0,
      "date": "2026-01-02",
      "rebased_return_pct": 0.5141388174807198,
      "relative_trading_value": 0.6641655609946481,
      "trading_value": 6285653440.0
    },
    {
      "close": 7800.0,
      "date": "2026-01-05",
      "rebased_return_pct": 0.2570694087403599,
      "relative_trading_value": 0.6033645830148916,
      "trading_value": 5470522200.0
    },
    {
      "close": 7790.0,
      "date": "2026-01-06",
      "rebased_return_pct": 0.12853470437017994,
      "relative_trading_value": 0.4184224775793787,
      "trading_value": 3626517650.0
    },
    {
      "close": 7510.0,
      "date": "2026-01-07",
      "rebased_return_pct": -3.470437017994859,
      "relative_trading_value": 0.5609035865950127,
      "trading_value": 4578689290.0
    },
    {
      "close": 7160.0,
      "date": "2026-01-08",
      "rebased_return_pct": -7.969151670951156,
      "relative_trading_value": 0.9522940638485671,
      "trading_value": 7463326240.0
    },
    {
      "close": 7320.0,
      "date": "2026-01-09",
      "rebased_return_pct": -5.912596401028278,
      "relative_trading_value": 0.4463783102656353,
      "trading_value": 3484451760.0
    },
    {
      "close": 7260.0,
      "date": "2026-01-12",
      "rebased_return_pct": -6.683804627249357,
      "relative_trading_value": 0.32366927273835655,
      "trading_value": 2418981180.0
    },
    {
      "close": 7290.0,
      "date": "2026-01-13",
      "rebased_return_pct": -6.298200514138817,
      "relative_trading_value": 0.46568186254120136,
      "trading_value": 3312196920.0
    },
    {
      "close": 7240.0,
      "date": "2026-01-14",
      "rebased_return_pct": -6.940874035989718,
      "relative_trading_value": 0.3131942913906974,
      "trading_value": 2148267280.0
    },
    {
      "close": 7250.0,
      "date": "2026-01-15",
      "rebased_return_pct": -6.812339331619537,
      "relative_trading_value": 0.3910657478760943,
      "trading_value": 2567261250.0
    },
    {
      "close": 7280.0,
      "date": "2026-01-16",
      "rebased_return_pct": -6.426735218508997,
      "relative_trading_value": 0.7801334084566879,
      "trading_value": 4937958480.0
    },
    {
      "close": 7330.0,
      "date": "2026-01-19",
      "rebased_return_pct": -5.784061696658098,
      "relative_trading_value": 0.4807705427492834,
      "trading_value": 3005930380.0
    },
    {
      "close": 7530.0,
      "date": "2026-01-20",
      "rebased_return_pct": -3.2133676092544987,
      "relative_trading_value": 1.3275010804548406,
      "trading_value": 8073138900.0
    },
    {
      "close": 7550.0,
      "date": "2026-01-21",
      "rebased_return_pct": -2.956298200514139,
      "relative_trading_value": 0.853269100045597,
      "trading_value": 5274090250.0
    },
    {
      "close": 7580.0,
      "date": "2026-01-22",
      "rebased_return_pct": -2.570694087403599,
      "relative_trading_value": 0.8743407657223842,
      "trading_value": 5430933560.0
    },
    {
      "close": 7730.0,
      "date": "2026-01-23",
      "rebased_return_pct": -0.6426735218508998,
      "relative_trading_value": 1.1781930969988688,
      "trading_value": 6278259620.0
    },
    {
      "close": 7910.0,
      "date": "2026-01-26",
      "rebased_return_pct": 1.6709511568123392,
      "relative_trading_value": 2.169565762495129,
      "trading_value": 10637162340.0
    },
    {
      "close": 8000.0,
      "date": "2026-01-27",
      "rebased_return_pct": 2.827763496143959,
      "relative_trading_value": 2.1254856242581144,
      "trading_value": 10775040000.0
    },
    {
      "close": 8260.0,
      "date": "2026-01-28",
      "rebased_return_pct": 6.169665809768637,
      "relative_trading_value": 2.621916143009606,
      "trading_value": 13853192920.0
    },
    {
      "close": 8800.0,
      "date": "2026-01-29",
      "rebased_return_pct": 13.110539845758353,
      "relative_trading_value": 6.4538225716929984,
      "trading_value": 37189460000.0
    },
    {
      "close": 8500.0,
      "date": "2026-01-30",
      "rebased_return_pct": 9.254498714652955,
      "relative_trading_value": 1.8615766348525007,
      "trading_value": 13664999500.0
    },
    {
      "close": 8320.0,
      "date": "2026-02-02",
      "rebased_return_pct": 6.940874035989718,
      "relative_trading_value": 1.4172207448792966,
      "trading_value": 10926090240.0
    },
    {
      "close": 8630.0,
      "date": "2026-02-03",
      "rebased_return_pct": 10.925449871465295,
      "relative_trading_value": 1.3204445972966798,
      "trading_value": 10540181460.0
    },
    {
      "close": 8740.0,
      "date": "2026-02-04",
      "rebased_return_pct": 12.339331619537274,
      "relative_trading_value": 0.950059525886297,
      "trading_value": 7912077280.0
    },
    {
      "close": 8580.0,
      "date": "2026-02-05",
      "rebased_return_pct": 10.282776349614396,
      "relative_trading_value": 1.0987478547288532,
      "trading_value": 9333478440.0
    },
    {
      "close": 9380.0,
      "date": "2026-02-06",
      "rebased_return_pct": 20.565552699228792,
      "relative_trading_value": 8.016588730998492,
      "trading_value": 68847727340.0
    },
    {
      "close": 9400.0,
      "date": "2026-02-09",
      "rebased_return_pct": 20.822622107969153,
      "relative_trading_value": 1.4549070884677548,
      "trading_value": 17249846000.0
    },
    {
      "close": 9050.0,
      "date": "2026-02-10",
      "rebased_return_pct": 16.323907455012854,
      "relative_trading_value": 0.8332324982548344,
      "trading_value": 10496950200.0
    },
    {
      "close": 9150.0,
      "date": "2026-02-11",
      "rebased_return_pct": 17.60925449871465,
      "relative_trading_value": 0.6678783472058095,
      "trading_value": 8653768050.0
    },
    {
      "close": 9270.0,
      "date": "2026-02-12",
      "rebased_return_pct": 19.151670951156813,
      "relative_trading_value": 0.8149837741352725,
      "trading_value": 10824921990.0
    },
    {
      "close": 9110.0,
      "date": "2026-02-13",
      "rebased_return_pct": 17.09511568123393,
      "relative_trading_value": 0.7829581846508961,
      "trading_value": 10722816180.0
    },
    {
      "close": 9440.0,
      "date": "2026-02-19",
      "rebased_return_pct": 21.336760925449873,
      "relative_trading_value": 1.4966654311579959,
      "trading_value": 20930122560.0
    },
    {
      "close": 9550.0,
      "date": "2026-02-20",
      "rebased_return_pct": 22.750642673521853,
      "relative_trading_value": 1.6623462406325475,
      "trading_value": 24736897050.0
    },
    {
      "close": 8850.0,
      "date": "2026-02-23",
      "rebased_return_pct": 13.753213367609254,
      "relative_trading_value": 1.7568909744931978,
      "trading_value": 27607610400.0
    },
    {
      "close": 8390.0,
      "date": "2026-02-24",
      "rebased_return_pct": 7.840616966580977,
      "relative_trading_value": 1.783669823935543,
      "trading_value": 30020191880.0
    },
    {
      "close": 8350.0,
      "date": "2026-02-25",
      "rebased_return_pct": 7.326478149100257,
      "relative_trading_value": 0.7910548846553205,
      "trading_value": 14286482600.0
    },
    {
      "close": 8390.0,
      "date": "2026-02-26",
      "rebased_return_pct": 7.840616966580977,
      "relative_trading_value": 0.7624796683516898,
      "trading_value": 14075718420.0
    },
    {
      "close": 8410.0,
      "date": "2026-02-27",
      "rebased_return_pct": 8.097686375321336,
      "relative_trading_value": 0.8774324238787995,
      "trading_value": 16348653140.0
    },
    {
      "close": 7900.0,
      "date": "2026-03-03",
      "rebased_return_pct": 1.5424164524421593,
      "relative_trading_value": 1.1737944537322351,
      "trading_value": 22197696500.0
    },
    {
      "close": 7000.0,
      "date": "2026-03-04",
      "rebased_return_pct": -10.025706940874036,
      "relative_trading_value": 1.1065718761850292,
      "trading_value": 21388136000.0
    },
    {
      "close": 7880.0,
      "date": "2026-03-05",
      "rebased_return_pct": 1.2853470437017995,
      "relative_trading_value": 1.0806069837684116,
      "trading_value": 20032528120.0
    },
    {
      "close": 8280.0,
      "date": "2026-03-06",
      "rebased_return_pct": 6.426735218508997,
      "relative_trading_value": 0.6093230908001603,
      "trading_value": 11489758560.0
    },
    {
      "close": 7910.0,
      "date": "2026-03-09",
      "rebased_return_pct": 1.6709511568123392,
      "relative_trading_value": 0.5360194793839719,
      "trading_value": 10122608930.0
    },
    {
      "close": 9010.0,
      "date": "2026-03-10",
      "rebased_return_pct": 15.809768637532134,
      "relative_trading_value": 2.763400448021959,
      "trading_value": 52128508280.0
    },
    {
      "close": 11710.0,
      "date": "2026-03-11",
      "rebased_return_pct": 50.51413881748073,
      "relative_trading_value": 18.16364226690182,
      "trading_value": 382793693700.0
    },
    {
      "close": 12400.0,
      "date": "2026-03-12",
      "rebased_return_pct": 59.383033419023135,
      "relative_trading_value": 12.272356694863323,
      "trading_value": 487798342400.0
    },
    {
      "close": 12750.0,
      "date": "2026-03-13",
      "rebased_return_pct": 63.88174807197944,
      "relative_trading_value": 3.2729218708445282,
      "trading_value": 198650852250.0
    },
    {
      "close": 12340.0,
      "date": "2026-03-16",
      "rebased_return_pct": 58.61182519280206,
      "relative_trading_value": 0.4872389960892147,
      "trading_value": 33992381000.0
    },
    {
      "close": 12650.0,
      "date": "2026-03-17",
      "rebased_return_pct": 62.59640102827764,
      "relative_trading_value": 0.4003673873525842,
      "trading_value": 28402096250.0
    },
    {
      "close": 13220.0,
      "date": "2026-03-18",
      "rebased_return_pct": 69.9228791773779,
      "relative_trading_value": 0.5104624652083024,
      "trading_value": 36716289380.0
    },
    {
      "close": 12900.0,
      "date": "2026-03-19",
      "rebased_return_pct": 65.80976863753213,
      "relative_trading_value": 2.80838911414112,
      "trading_value": 205636062000.0
    },
    {
      "close": 13120.0,
      "date": "2026-03-20",
      "rebased_return_pct": 68.63753213367609,
      "relative_trading_value": 3.626970967443917,
      "trading_value": 300921553280.0
    },
    {
      "close": 12370.0,
      "date": "2026-03-23",
      "rebased_return_pct": 58.9974293059126,
      "relative_trading_value": 0.8189157556982645,
      "trading_value": 79408052220.0
    },
    {
      "close": 13320.0,
      "date": "2026-03-24",
      "rebased_return_pct": 71.2082262210797,
      "relative_trading_value": 1.948974257474411,
      "trading_value": 194314411080.0
    },
    {
      "close": 15910.0,
      "date": "2026-03-25",
      "rebased_return_pct": 104.49871465295631,
      "relative_trading_value": 7.638368173289367,
      "trading_value": 825220277750.0
    },
    {
      "close": 14340.0,
      "date": "2026-03-26",
      "rebased_return_pct": 84.31876606683805,
      "relative_trading_value": 1.0969462843649063,
      "trading_value": 162124498020.0
    },
    {
      "close": 14070.0,
      "date": "2026-03-27",
      "rebased_return_pct": 80.8483290488432,
      "relative_trading_value": 0.8094784035839001,
      "trading_value": 125621420190.0
    },
    {
      "close": 13440.0,
      "date": "2026-03-30",
      "rebased_return_pct": 72.75064267352185,
      "relative_trading_value": 0.3968262687760281,
      "trading_value": 63795930240.0
    },
    {
      "close": 12630.0,
      "date": "2026-03-31",
      "rebased_return_pct": 62.339331619537276,
      "relative_trading_value": 0.35933657422938237,
      "trading_value": 58621361940.0
    },
    {
      "close": 14570.0,
      "date": "2026-04-01",
      "rebased_return_pct": 87.27506426735219,
      "relative_trading_value": 1.7657763940600828,
      "trading_value": 291280598850.0
    },
    {
      "close": 15070.0,
      "date": "2026-04-02",
      "rebased_return_pct": 93.70179948586119,
      "relative_trading_value": 1.488211803067449,
      "trading_value": 265576696110.0
    },
    {
      "close": 16300.0,
      "date": "2026-04-03",
      "rebased_return_pct": 109.51156812339332,
      "relative_trading_value": 1.8344722647234515,
      "trading_value": 349890306900.0
    },
    {
      "close": 15640.0,
      "date": "2026-04-06",
      "rebased_return_pct": 101.02827763496146,
      "relative_trading_value": 0.6470491340088071,
      "trading_value": 134360268400.0
    },
    {
      "close": 14420.0,
      "date": "2026-04-07",
      "rebased_return_pct": 85.34704370179949,
      "relative_trading_value": 0.3564399840856886,
      "trading_value": 76229210260.0
    },
    {
      "close": 15100.0,
      "date": "2026-04-08",
      "rebased_return_pct": 94.08740359897172,
      "relative_trading_value": 0.44609406879355906,
      "trading_value": 95940432100.0
    },
    {
      "close": 14220.0,
      "date": "2026-04-09",
      "rebased_return_pct": 82.77634961439588,
      "relative_trading_value": 0.31732188322045135,
      "trading_value": 63694451520.0
    },
    {
      "close": 17080.0,
      "date": "2026-04-10",
      "rebased_return_pct": 119.53727506426735,
      "relative_trading_value": 4.277294078041505,
      "trading_value": 767859223320.0
    },
    {
      "close": 17350.0,
      "date": "2026-04-13",
      "rebased_return_pct": 123.00771208226222,
      "relative_trading_value": 1.927510532402293,
      "trading_value": 400884172600.0
    },
    {
      "close": 16880.0,
      "date": "2026-04-14",
      "rebased_return_pct": 116.96658097686374,
      "relative_trading_value": 0.7538196675484813,
      "trading_value": 170608134960.0
    },
    {
      "close": 18160.0,
      "date": "2026-04-15",
      "rebased_return_pct": 133.41902313624678,
      "relative_trading_value": 2.693847650907803,
      "trading_value": 628838777760.0
    },
    {
      "close": 16670.0,
      "date": "2026-04-16",
      "rebased_return_pct": 114.26735218508996,
      "relative_trading_value": 0.734951555850683,
      "trading_value": 193322606790.0
    },
    {
      "close": 16870.0,
      "date": "2026-04-17",
      "rebased_return_pct": 116.83804627249357,
      "relative_trading_value": 0.4997905303323108,
      "trading_value": 131157839400.0
    },
    {
      "close": 17070.0,
      "date": "2026-04-20",
      "rebased_return_pct": 119.40874035989717,
      "relative_trading_value": 0.6371815980290979,
      "trading_value": 161804259690.0
    },
    {
      "close": 16580.0,
      "date": "2026-04-21",
      "rebased_return_pct": 113.11053984575837,
      "relative_trading_value": 0.31276024676584,
      "trading_value": 80710047280.0
    },
    {
      "close": 16670.0,
      "date": "2026-04-22",
      "rebased_return_pct": 114.26735218508996,
      "relative_trading_value": 0.23243397990116763,
      "trading_value": 58660996520.0
    },
    {
      "close": 16470.0,
      "date": "2026-04-23",
      "rebased_return_pct": 111.69665809768638,
      "relative_trading_value": 0.22618198957984717,
      "trading_value": 48414042630.0
    },
    {
      "close": 16430.0,
      "date": "2026-04-24",
      "rebased_return_pct": 111.18251928020567,
      "relative_trading_value": 0.16000818180728366,
      "trading_value": 33339871010.0
    },
    {
      "close": 16780.0,
      "date": "2026-04-27",
      "rebased_return_pct": 115.68123393316196,
      "relative_trading_value": 0.3982054001857849,
      "trading_value": 81134135820.0
    },
    {
      "close": 15930.0,
      "date": "2026-04-28",
      "rebased_return_pct": 104.75578406169666,
      "relative_trading_value": 0.30545067104294743,
      "trading_value": 62500208040.0
    },
    {
      "close": 16070.0,
      "date": "2026-04-29",
      "rebased_return_pct": 106.55526992287918,
      "relative_trading_value": 0.17865558347983057,
      "trading_value": 36590506150.0
    },
    {
      "close": 17110.0,
      "date": "2026-04-30",
      "rebased_return_pct": 119.9228791773779,
      "relative_trading_value": 1.8931034425204658,
      "trading_value": 363619375930.0
    },
    {
      "close": 18640.0,
      "date": "2026-05-04",
      "rebased_return_pct": 139.58868894601542,
      "relative_trading_value": 2.099684495825564,
      "trading_value": 413591533680.0
    },
    {
      "close": 18440.0,
      "date": "2026-05-06",
      "rebased_return_pct": 137.01799485861184,
      "relative_trading_value": 1.9902442995947478,
      "trading_value": 398373279080.0
    },
    {
      "close": 18850.0,
      "date": "2026-05-07",
      "rebased_return_pct": 142.2879177377892,
      "relative_trading_value": 1.5733180343805828,
      "trading_value": 335688886650.0
    },
    {
      "close": 18200.0,
      "date": "2026-05-08",
      "rebased_return_pct": 133.9331619537275,
      "relative_trading_value": 0.7651230703501866,
      "trading_value": 173175384200.0
    },
    {
      "close": 18150.0,
      "date": "2026-05-11",
      "rebased_return_pct": 133.2904884318766,
      "relative_trading_value": 0.7001424972799642,
      "trading_value": 161171673300.0
    },
    {
      "close": 17400.0,
      "date": "2026-05-12",
      "rebased_return_pct": 123.6503856041131,
      "relative_trading_value": 0.44915301493417975,
      "trading_value": 105583408800.0
    },
    {
      "close": 16650.0,
      "date": "2026-05-13",
      "rebased_return_pct": 114.01028277634961,
      "relative_trading_value": 0.24301370155782237,
      "trading_value": 49078672200.0
    },
    {
      "close": 16260.0,
      "date": "2026-05-14",
      "rebased_return_pct": 108.99742930591259,
      "relative_trading_value": 0.36406522803377406,
      "trading_value": 67122044220.0
    },
    {
      "close": 15600.0,
      "date": "2026-05-15",
      "rebased_return_pct": 100.51413881748073,
      "relative_trading_value": 0.24454531941468355,
      "trading_value": 43821024000.0
    },
    {
      "close": 15400.0,
      "date": "2026-05-18",
      "rebased_return_pct": 97.94344473007712,
      "relative_trading_value": 0.2676683135483529,
      "trading_value": 40134987200.0
    },
    {
      "close": 15130.0,
      "date": "2026-05-19",
      "rebased_return_pct": 94.47300771208226,
      "relative_trading_value": 0.2934432032267545,
      "trading_value": 41752157930.0
    },
    {
      "close": 14790.0,
      "date": "2026-05-20",
      "rebased_return_pct": 90.10282776349614,
      "relative_trading_value": 0.30238150451507617,
      "trading_value": 41672200470.0
    },
    {
      "close": 15740.0,
      "date": "2026-05-21",
      "rebased_return_pct": 102.31362467866323,
      "relative_trading_value": 0.43250967887471337,
      "trading_value": 57007682900.0
    },
    {
      "close": 18130.0,
      "date": "2026-05-22",
      "rebased_return_pct": 133.03341902313625,
      "relative_trading_value": 2.2310591273561142,
      "trading_value": 291424520800.0
    },
    {
      "close": 18340.0,
      "date": "2026-05-26",
      "rebased_return_pct": 135.73264781491002,
      "relative_trading_value": 0.8163469451708597,
      "trading_value": 116133336620.0
    },
    {
      "close": 17150.0,
      "date": "2026-05-27",
      "rebased_return_pct": 120.43701799485862,
      "relative_trading_value": 0.39328142003945793,
      "trading_value": 57279765200.0
    },
    {
      "close": 15870.0,
      "date": "2026-05-28",
      "rebased_return_pct": 103.98457583547558,
      "relative_trading_value": 0.32898931677872206,
      "trading_value": 48309692430.0
    },
    {
      "close": 16000.0,
      "date": "2026-05-29",
      "rebased_return_pct": 105.6555269922879,
      "relative_trading_value": 0.3448388215079625,
      "trading_value": 50071120000.0
    },
    {
      "close": 15200.0,
      "date": "2026-06-01",
      "rebased_return_pct": 95.37275064267352,
      "relative_trading_value": 0.2273875070429569,
      "trading_value": 32875700000.0
    },
    {
      "close": 14410.0,
      "date": "2026-06-02",
      "rebased_return_pct": 85.21850899742931,
      "relative_trading_value": 0.2153520463885952,
      "trading_value": 31095612790.0
    },
    {
      "close": 14990.0,
      "date": "2026-06-04",
      "rebased_return_pct": 92.67352185089975,
      "relative_trading_value": 0.2991653257850121,
      "trading_value": 38223795470.0
    },
    {
      "close": 13510.0,
      "date": "2026-06-05",
      "rebased_return_pct": 73.65038560411311,
      "relative_trading_value": 0.189759049345145,
      "trading_value": 20683688410.0
    },
    {
      "close": 12550.0,
      "date": "2026-06-08",
      "rebased_return_pct": 61.311053984575835,
      "relative_trading_value": 0.24479926784946326,
      "trading_value": 22060151550.0
    },
    {
      "close": 13290.0,
      "date": "2026-06-09",
      "rebased_return_pct": 70.82262210796915,
      "relative_trading_value": 0.40014660753133974,
      "trading_value": 29784444930.0
    },
    {
      "close": 12150.0,
      "date": "2026-06-10",
      "rebased_return_pct": 56.169665809768645,
      "relative_trading_value": 0.3635351572935478,
      "trading_value": 24452932050.0
    },
    {
      "close": 12420.0,
      "date": "2026-06-11",
      "rebased_return_pct": 59.6401028277635,
      "relative_trading_value": 0.42136891586276465,
      "trading_value": 25462627020.0
    },
    {
      "close": 12790.0,
      "date": "2026-06-12",
      "rebased_return_pct": 64.39588688946016,
      "relative_trading_value": 0.46582189864936174,
      "trading_value": 26282746550.0
    },
    {
      "close": 12970.0,
      "date": "2026-06-15",
      "rebased_return_pct": 66.70951156812339,
      "relative_trading_value": 0.22639035554467277,
      "trading_value": 12515427440.0
    },
    {
      "close": 12810.0,
      "date": "2026-06-16",
      "rebased_return_pct": 64.65295629820051,
      "relative_trading_value": 0.3071322957238497,
      "trading_value": 16140471900.0
    },
    {
      "close": 12830.0,
      "date": "2026-06-17",
      "rebased_return_pct": 64.91002570694087,
      "relative_trading_value": 0.24253988315484418,
      "trading_value": 12410317870.0
    },
    {
      "close": 12370.0,
      "date": "2026-06-18",
      "rebased_return_pct": 58.9974293059126,
      "relative_trading_value": 0.21991709850359745,
      "trading_value": 10947895320.0
    },
    {
      "close": 11830.0,
      "date": "2026-06-19",
      "rebased_return_pct": 52.056555269922875,
      "relative_trading_value": 0.3254535146793853,
      "trading_value": 15700432930.0
    }
  ]
}